argpi/__init__.py
argpi/_dummy.py
argpi/_dummy.pyi
argpi/core.py
argpi/core.pyi
argpi/pathways.py
argpi/pathways.pyi
argpi/exceptions/__init__.py
argpi/exceptions/_dummy.py
argpi/exceptions/_dummy.pyi
argpi/exceptions/decorators.py
argpi/exceptions/decorators.pyi
argpi/exceptions/pathways.py
argpi/exceptions/pathways.pyi
argpi/utils/__init__.py
argpi/utils/decorators.py
argpi/utils/decorators.pyi
argpi-1.2.1.dist-info/LICENSE
argpi-1.2.1.dist-info/METADATA
argpi-1.2.1.dist-info/WHEEL
argpi-1.2.1.dist-info/top_level.txt
argpi-1.2.1.dist-info/RECORD
